features/steps/__init__.py
features/steps/add.py
features/steps/check.py
features/steps/context.py
features/steps/run.py
features/steps/validate.py
nitpicker/__init__.py
nitpicker/__main__.py
nitpicker/nitpicker.py
nitpicker/commands/__init__.py
nitpicker/commands/add_command_handler.py
nitpicker/commands/check_command_handler.py
nitpicker/commands/helpers.py
nitpicker/commands/list_command_handler.py
nitpicker/commands/run_command_handler.py
nitpicker/commands/validate_command_handler.py
nitpicker/report_generator/REPORT_TEMPLATE.md
nitpicker/report_generator/__init__.py
nitpicker/report_generator/generator.py
nitpicker/vcs/__init__.py
nitpicker/vcs/git_adapter.py
nitpicker/vcs/null_adapter.py
nitpicker/vcs/vcs_adapter.py
nitpicker/vcs/vcs_factory.py
nitpicker-0.4.2.dist-info/DESCRIPTION.rst
nitpicker-0.4.2.dist-info/METADATA
nitpicker-0.4.2.dist-info/RECORD
nitpicker-0.4.2.dist-info/WHEEL
nitpicker-0.4.2.dist-info/entry_points.txt
nitpicker-0.4.2.dist-info/metadata.json
nitpicker-0.4.2.dist-info/top_level.txt
