Metadata-Version: 2.0
Name: nitpicker
Version: 0.4.2
Summary: A simple CLI tool for QA
Home-page: https://github.com/flipback/nitpicker
Author: Aleksey Timin
Author-email: atimin@gmail.com
License: MIT
Platform: UNKNOWN
Requires-Dist: click (>=6.7)
Requires-Dist: colorama (>=0.3.9)
Requires-Dist: gitpython (>=2.1)
Requires-Dist: mako (>=1.0)
Requires-Dist: pyyaml (>=3.13)
Requires-Dist: schema (>=0.6)
